setup.cfg
setup.py
pyreport/__init__.py
pyreport/code_hasher.py
pyreport/options.py
pyreport/pyreport.py
pyreport/version.py
pyreport.egg-info/PKG-INFO
pyreport.egg-info/SOURCES.txt
pyreport.egg-info/dependency_links.txt
pyreport.egg-info/entry_points.txt
pyreport.egg-info/not-zip-safe
pyreport.egg-info/top_level.txt