Metadata-Version: 1.0
Name: pyreport
Version: 0.3.0
Summary: 
